[
  {
    "name": "StreamStats-Setup",
    "organization": "U.S. Geological Survey",
    "description": "Setup scripts and information for StreamStats",
    "version": "v0.0.0",
    "status": "Development"

    "permissions": {
      "usageType": "openSource",
      "licenses": [
        {
          "name": "Public Domain",
          "URL": "https://github.com/usgs/StreamStats-Setup/blob/master/LICENSE.md"
        }
      ]
    },

    "homepageURL": null,
    "downloadURL": "https://github.com/USGS-WiM/StreamStats-Setup/archive/master.zip",
    "disclaimerURL": "https://github.com/USGS-WiM/StreamStats-Setup/blob/master/DISCLAIMER.md",
    "repositoryUrl": "https://github.com/USGS-WiM/StreamStats-Setup",
    "vcs": "git",

    "laborHours": null,

    "tags": [
      "streamstats",
      "setup",
      "scripts"
    ],

    "languages": [
      "html",
      "css"
    ],

    "contact": {
      "name": "Marty Smith",
      "email": "marsmith@usgs.gov"
    },

    "date": {
      "metadataLastUpdated": "2018-02-16"
    }
  }
]
